dbtsdk/Dbt.py
dbtsdk/__init__.py
dbtsdk-0.3.dist-info/LICENSE
dbtsdk-0.3.dist-info/METADATA
dbtsdk-0.3.dist-info/WHEEL
dbtsdk-0.3.dist-info/top_level.txt
dbtsdk-0.3.dist-info/RECORD
