Metadata-Version: 2.1
Name: dbtsdk
Version: 0.3
Summary: DBT API SDK for Python
Home-page: https://github.com/Nilpo/dbt-sdk-python
Author: Rob Dunham
Author-email: devnilpo@gmail.com
License: UNKNOWN
Platform: UNKNOWN
Classifier: Programming Language :: Python :: 3
Classifier: License :: OSI Approved :: MIT License
Classifier: Operating System :: OS Independent
